<?xml version="1.0"?>
<testResults>
  <FitNesseVersion>v20210410</FitNesseVersion>
  <rootPath>FitNesse.FullReferenceGuide.UserGuide.WritingAcceptanceTests.SliM.DefineTableType</rootPath>
  <result>
    <counts>
      <right>11</right>
      <wrong>0</wrong>
      <ignores>0</ignores>
      <exceptions>0</exceptions>
    </counts>
    <date>2021-05-21T14:34:42+05:30</date>
    <runTimeInMillis>83</runTimeInMillis>
    <content>&lt;div class="collapsible closed"&gt;&lt;ul&gt;&lt;li&gt;&lt;a href='#' class='expandall'&gt;Expand&lt;/a&gt;&lt;/li&gt;&lt;li&gt;&lt;a href='#' class='collapseall'&gt;Collapse&lt;/a&gt;&lt;/li&gt;&lt;/ul&gt;
	&lt;p class="title"&gt;Included page: &lt;a href="FitNesse.FullReferenceGuide.UserGuide.WritingAcceptanceTests.SliM.SetUp"&gt;.FitNesse.FullReferenceGuide.UserGuide.WritingAcceptanceTests.SliM.SetUp&lt;/a&gt; &lt;a href="FitNesse.FullReferenceGuide.UserGuide.WritingAcceptanceTests.SliM.SetUp?edit&amp;amp;redirectToReferer=true&amp;amp;redirectAction=" class="edit"&gt;(edit)&lt;/a&gt;&lt;/p&gt;
	&lt;div&gt;&lt;div class="collapsible closed"&gt;&lt;ul&gt;&lt;li&gt;&lt;a href='#' class='expandall'&gt;Expand&lt;/a&gt;&lt;/li&gt;&lt;li&gt;&lt;a href='#' class='collapseall'&gt;Collapse&lt;/a&gt;&lt;/li&gt;&lt;/ul&gt;
	&lt;p class="title"&gt;setup&lt;/p&gt;
	&lt;div&gt;&lt;table&gt;
	&lt;tr class="slimRowTitle"&gt;
		&lt;td&gt;import&lt;/td&gt;
	&lt;/tr&gt;
	&lt;tr class="slimRowColor0"&gt;
		&lt;td&gt;&lt;span class="pass"&gt;fitnesse.slim.test&lt;/span&gt;&lt;/td&gt;
	&lt;/tr&gt;
	&lt;tr class="slimRowColor1"&gt;
		&lt;td&gt;&lt;span class="pass"&gt;fitnesse.fixtures&lt;/span&gt;&lt;/td&gt;
	&lt;/tr&gt;
&lt;/table&gt;
&lt;br/&gt;&lt;/div&gt;
&lt;/div&gt;
&lt;/div&gt;
&lt;/div&gt;
&lt;br/&gt;&lt;table&gt;
	&lt;tr class="slimRowTitle"&gt;
		&lt;td colspan="2"&gt;Define table type&lt;/td&gt;
	&lt;/tr&gt;
	&lt;tr class="slimRowTitle"&gt;
		&lt;td&gt;Bowling&lt;/td&gt;
		&lt;td&gt;as Table&lt;/td&gt;
	&lt;/tr&gt;
&lt;/table&gt;
&lt;br/&gt;The "Define table type" table is designed to help you write more readable tests. &lt;br/&gt;&lt;br/&gt;In the above example we have defined Bowling as a Table fixture.   Once you have defined the type like this you can just use "Bowling" in your test table and don't need to write "Table: Bowling".&lt;br/&gt;&lt;br/&gt;For example, the following table will now work:&lt;br/&gt;&lt;table&gt;
	&lt;tr class="slimRowTitle"&gt;
		&lt;td colspan="21"&gt;&lt;span class="pass"&gt;Bowling&lt;/span&gt;&lt;/td&gt;
	&lt;/tr&gt;
	&lt;tr class="slimRowTitle"&gt;
		&lt;td&gt;3&lt;/td&gt;
		&lt;td&gt;5&lt;/td&gt;
		&lt;td&gt;4&lt;/td&gt;
		&lt;td&gt;/&lt;/td&gt;
		&lt;td&gt;X&lt;/td&gt;
		&lt;td&gt;&lt;/td&gt;
		&lt;td&gt;X&lt;/td&gt;
		&lt;td&gt;&lt;/td&gt;
		&lt;td&gt;3&lt;/td&gt;
		&lt;td&gt;4&lt;/td&gt;
		&lt;td&gt;6&lt;/td&gt;
		&lt;td&gt;/&lt;/td&gt;
		&lt;td&gt;7&lt;/td&gt;
		&lt;td&gt;2&lt;/td&gt;
		&lt;td&gt;3&lt;/td&gt;
		&lt;td&gt;4&lt;/td&gt;
		&lt;td&gt;9&lt;/td&gt;
		&lt;td&gt;-&lt;/td&gt;
		&lt;td&gt;4&lt;/td&gt;
		&lt;td&gt;/&lt;/td&gt;
		&lt;td&gt;3&lt;/td&gt;
	&lt;/tr&gt;
	&lt;tr class="slimRowColor1"&gt;
		&lt;td&gt;&lt;/td&gt;
		&lt;td&gt;&lt;span class="pass"&gt;8&lt;/span&gt;&lt;/td&gt;
		&lt;td&gt;&lt;/td&gt;
		&lt;td&gt;&lt;span class="pass"&gt;28&lt;/span&gt;&lt;/td&gt;
		&lt;td&gt;&lt;/td&gt;
		&lt;td&gt;&lt;span class="pass"&gt;51&lt;/span&gt;&lt;/td&gt;
		&lt;td&gt;&lt;/td&gt;
		&lt;td&gt;&lt;span class="pass"&gt;68&lt;/span&gt;&lt;/td&gt;
		&lt;td&gt;&lt;/td&gt;
		&lt;td&gt;&lt;span class="pass"&gt;75&lt;/span&gt;&lt;/td&gt;
		&lt;td&gt;&lt;/td&gt;
		&lt;td&gt;&lt;span class="pass"&gt;92&lt;/span&gt;&lt;/td&gt;
		&lt;td&gt;&lt;/td&gt;
		&lt;td&gt;&lt;span class="pass"&gt;101&lt;/span&gt;&lt;/td&gt;
		&lt;td&gt;&lt;/td&gt;
		&lt;td&gt;&lt;span class="pass"&gt;108&lt;/span&gt;&lt;/td&gt;
		&lt;td&gt;&lt;/td&gt;
		&lt;td&gt;&lt;span class="pass"&gt;117&lt;/span&gt;&lt;/td&gt;
		&lt;td&gt;&lt;/td&gt;
		&lt;td&gt;&lt;/td&gt;
		&lt;td&gt;&lt;span class="pass"&gt;127&lt;/span&gt;&lt;/td&gt;
	&lt;/tr&gt;
&lt;/table&gt;
&lt;br/&gt;Using this fixture makes your test pages easier to read, especially for project managers, BA's and Product owners who might not understand how Fitnesse works.   (The "table:" or "query:" strings are just a test implementation detail and therefore it is good to leave them out where ever possible.)&lt;br/&gt;&lt;br/&gt;Hint: Try putting the "Define Table Type" fixtures in the same place as your "Import" fixtures.   The setup pages are a good place for these!&lt;br/&gt;&lt;br/&gt;</content>
    <relativePageName>DefineTableType</relativePageName>
    <instructions>
      <instructionResult>
        <instruction>{id='import_0_0', instruction='import', path='fitnesse.slim.test'}</instruction>
        <slimResult>pass(fitnesse.slim.test)</slimResult>
        <expectation>
          <status>pass</status>
          <instructionId>import_0_0</instructionId>
          <col>0</col>
          <row>1</row>
          <type>ImportExpectation</type>
          <evaluationMessage>fitnesse.slim.test</evaluationMessage>
        </expectation>
      </instructionResult>
      <instructionResult>
        <instruction>{id='import_0_1', instruction='import', path='fitnesse.fixtures'}</instruction>
        <slimResult>pass(fitnesse.fixtures)</slimResult>
        <expectation>
          <status>pass</status>
          <instructionId>import_0_1</instructionId>
          <col>0</col>
          <row>2</row>
          <type>ImportExpectation</type>
          <evaluationMessage>fitnesse.fixtures</evaluationMessage>
        </expectation>
      </instructionResult>
      <instructionResult>
        <instruction>{id='tableTable_1_0', instruction='make', instanceName='tableTable_1', className='Bowling', args=[]}</instruction>
        <slimResult>pass(Bowling)</slimResult>
        <expectation>
          <status>pass</status>
          <instructionId>tableTable_1_0</instructionId>
          <col>0</col>
          <row>0</row>
          <type>ConstructionExpectation</type>
          <evaluationMessage>Bowling</evaluationMessage>
        </expectation>
      </instructionResult>
      <instructionResult>
        <instruction>{id='tableTable_1_1', instruction='call', instanceName='tableTable_1', methodName='doTable', args=[[[3, 5, 4, /, X, , X, , 3, 4, 6, /, 7, 2, 3, 4, 9, -, 4, /, 3], [, 8, , 28, , 51, , 68, , 75, , 92, , 101, , 108, , 117, , , 127]]]}</instruction>
        <slimResult>pass()</slimResult>
        <expectation>
          <status>pass</status>
          <instructionId>tableTable_1_1</instructionId>
          <type>TableTableExpectation</type>
        </expectation>
      </instructionResult>
    </instructions>
  </result>
  <executionLog>
    <testSystem>slim:fitnesse.slim.SlimService</testSystem>
    <command>java -cp lib/*.jar;C:\Users\nkauv\FitnesseExamples\fitnesse-standalone.jar fitnesse.slim.SlimService 1</command>
    <exitCode>0</exitCode>
    <stdOut></stdOut>
    <stdErr></stdErr>
  </executionLog>
  <finalCounts>
    <right>1</right>
    <wrong>0</wrong>
    <ignores>0</ignores>
    <exceptions>0</exceptions>
  </finalCounts>
  <totalRunTimeInMillis>459</totalRunTimeInMillis>
</testResults>

